[
    {
        "team": "Aldridge CC"
    },
    {
        "team": "Armitage CC"
    },
    {
        "team": "Beacon CC"
    },
    {
        "team": "Bloxwich CC"
    },
    {
        "team": "Brewood CC"
    },
    {
        "team": "Burntwood St Matthew's CC"
    },
    {
        "team": "Cannock CC"
    },
    {
        "team": "Codsall CC"
    },
    {
        "team": "Coseley CC"
    },
    {
        "team": "Elford CC"
    },
    {
        "team": "Fordhouses CC"
    },
    {
        "team": "Hammerwich CC"
    },
    {
        "team": "Hawkins Sports CC"
    },
    {
        "team": "Highcroft & Great Barr CC"
    },
    {
        "team": "Lichfield CC"
    },
    {
        "team": "Milford Hall CC"
    },
    {
        "team": "Old Wulfrunians Tettenhall CC"
    },
    {
        "team": "Pelsall CC"
    },
    {
        "team": "Penkridge CC"
    },
    {
        "team": "Penn CC"
    },
    {
        "team": "Rugeley CC"
    },
    {
        "team": "Rushall CC"
    },
    {
        "team": "Springhill CC"
    },
    {
        "team": "Springvale CC"
    },
    {
        "team": "Swindon CC"
    },
    {
        "team": "Tamworth CC"
    },
    {
        "team": "Walsall CC"
    },
    {
        "team": "Walsall YPF CC"
    },
    {
        "team": "Wednesbury CC"
    },
    {
        "team": "West Bromwich Dartmouth CC"
    },
    {
        "team": "Whitmore Reans CC"
    },
    {
        "team": "Whittington CC"
    },
    {
        "team": "Wightwick & Finchfield CC"
    },
    {
        "team": "Wolverhampton CC"
    },
    {
        "team": "Wombourne CC"
    },
    {
        "team": "Stafford CC"
    }
]
